[
  {
    "day": "2023-01-08T00:00:00.000Z",
    "id": "106912c",
    "title": "[FRESH EP] ZelooperZ - Might Not Make It",
    "permalink": "/r/hiphopheads/comments/106912c/fresh_ep_zelooperz_might_not_make_it/",
    "url": "https://zelooperz.bandcamp.com/album/might-not-make-it",
    "author": "TheOddScreen",
    "created_utc": 1673150167,
    "score": 257,
    "daily_sent": false
  },
  {
    "day": "2023-01-08T00:00:00.000Z",
    "id": "106wnid",
    "title": "[Fresh] MC Paul Barman [feat. Jordan Katz & Eric Kufs] - Fall in Love with Yourself (2022)",
    "permalink": "/r/hiphopheads/comments/106wnid/fresh_mc_paul_barman_feat_jordan_katz_eric_kufs/",
    "url": "https://youtube.com/watch?v=DVkGUyvfR-8&feature=share",
    "author": "Cart00nish",
    "created_utc": 1673217482,
    "score": 15,
    "daily_sent": false
  },
  {
    "day": "2023-01-08T00:00:00.000Z",
    "id": "106qb6x",
    "title": "[FRESH] Trae Tha Truth - Bring Tha Pain Freestyle (Official Music Video)",
    "permalink": "/r/hiphopheads/comments/106qb6x/fresh_trae_tha_truth_bring_tha_pain_freestyle/",
    "url": "https://www.youtube.com/watch?v=YirnVOm8W_Y",
    "author": "darkfar",
    "created_utc": 1673202494,
    "score": 10,
    "daily_sent": false
  },
  {
    "day": "2023-01-08T00:00:00.000Z",
    "id": "106rwco",
    "title": "[FRESH ALBUM] 03 Greedo - Free 03",
    "permalink": "/r/hiphopheads/comments/106rwco/fresh_album_03_greedo_free_03/",
    "url": "https://open.spotify.com/album/2UfVYQnUerGa6XhbJYlaWS",
    "author": "maloboosie",
    "created_utc": 1673206273,
    "score": 9,
    "daily_sent": false
  },
  {
    "day": "2023-01-08T00:00:00.000Z",
    "id": "106owl3",
    "title": "[FRESH] Radubai - Call God (Official Music Video)",
    "permalink": "/r/hiphopheads/comments/106owl3/fresh_radubai_call_god_official_music_video/",
    "url": "https://www.youtube.com/watch?v=KzqKV-GW5Fo",
    "author": "darkfar",
    "created_utc": 1673199162,
    "score": 7,
    "daily_sent": false
  },
  {
    "day": "2023-01-08T00:00:00.000Z",
    "id": "106jkfo",
    "title": "[Fresh] Eto Ft. Charlie Mac - Exclusive: New Shxt (Freestyle)",
    "permalink": "/r/hiphopheads/comments/106jkfo/fresh_eto_ft_charlie_mac_exclusive_new_shxt/",
    "url": "https://youtu.be/FWhGVgL0aCo",
    "author": "Akverse47",
    "created_utc": 1673185392,
    "score": 5,
    "daily_sent": false
  },
  {
    "day": "2023-01-08T00:00:00.000Z",
    "id": "106yd5t",
    "title": "[FRESH] Jay Rocc x Certified Lotto - Code 33 (Official Music Video)",
    "permalink": "/r/hiphopheads/comments/106yd5t/fresh_jay_rocc_x_certified_lotto_code_33_official/",
    "url": "https://www.youtube.com/watch?v=98LCNfqw0fk",
    "author": "darkfar",
    "created_utc": 1673221610,
    "score": 4,
    "daily_sent": false
  },
  {
    "day": "2023-01-08T00:00:00.000Z",
    "id": "106u7qb",
    "title": "[FRESH] Kai Bandz - Oh Boy Freestyle (Official Music Video)",
    "permalink": "/r/hiphopheads/comments/106u7qb/fresh_kai_bandz_oh_boy_freestyle_official_music/",
    "url": "https://www.youtube.com/watch?v=TNhX2Oc1b7I",
    "author": "darkfar",
    "created_utc": 1673211805,
    "score": 3,
    "daily_sent": false
  },
  {
    "day": "2023-01-08T00:00:00.000Z",
    "id": "10645dc",
    "title": "[FRESH] Cassanova300 - Top Tier (Official Music Video)",
    "permalink": "/r/hiphopheads/comments/10645dc/fresh_cassanova300_top_tier_official_music_video/",
    "url": "https://www.youtube.com/watch?v=7wSwIlZuADY",
    "author": "darkfar",
    "created_utc": 1673136691,
    "score": 2,
    "daily_sent": false
  },
  {
    "day": "2023-01-08T00:00:00.000Z",
    "id": "106spo1",
    "title": "[FRESH] Miyaa V - EOS (Official Music Video)",
    "permalink": "/r/hiphopheads/comments/106spo1/fresh_miyaa_v_eos_official_music_video/",
    "url": "https://www.youtube.com/watch?v=q4yw318f75g",
    "author": "darkfar",
    "created_utc": 1673208229,
    "score": 1,
    "daily_sent": false
  },
  {
    "day": "2023-01-08T00:00:00.000Z",
    "id": "106mrug",
    "title": "[FRESH] 5AR - LOOP - Experimental rap, fast flows, melodic hooks over DnB/trap drums and a Kingdom Hearts sample",
    "permalink": "/r/hiphopheads/comments/106mrug/fresh_5ar_loop_experimental_rap_fast_flows/",
    "url": "https://open.spotify.com/track/5PdNYyaoxqhDrXfEyOxrgZ?si=8efc2741e06c4e44",
    "author": "5AR5AR5AR",
    "created_utc": 1673193988,
    "score": 1,
    "daily_sent": false
  },
  {
    "day": "2023-01-08T00:00:00.000Z",
    "id": "1068ffe",
    "title": "[Fresh Video] C0REY P - My Mind (Song about not caring who believes because I see a vision others don’t)",
    "permalink": "/r/hiphopheads/comments/1068ffe/fresh_video_c0rey_p_my_mind_song_about_not_caring/",
    "url": "https://v.redd.it/w2dwvoq32saa1",
    "author": "coreyrp",
    "created_utc": 1673148405,
    "score": 0,
    "daily_sent": false
  }
]