[
  {
    "day": "2023-12-16T00:00:00.000Z",
    "id": "18jvkv5",
    "title": "[FRESH] Juice WRLD - Lace It (feat. Eminem & benny blanco)",
    "permalink": "/r/hiphopheads/comments/18jvkv5/fresh_juice_wrld_lace_it_feat_eminem_benny_blanco/",
    "url": "https://www.reddit.com/r/hiphopheads/comments/18jvkv5/fresh_juice_wrld_lace_it_feat_eminem_benny_blanco/",
    "author": "TharealSergi",
    "created_utc": 1702746375,
    "score": 779,
    "daily_sent": false
  },
  {
    "day": "2023-12-16T00:00:00.000Z",
    "id": "18ji5wm",
    "title": "[FRESH VIDEO] Famous Dex, Rich The Kid & Jay Critch - Big Dawg (Directed by Cole Bennett)",
    "permalink": "/r/hiphopheads/comments/18ji5wm/fresh_video_famous_dex_rich_the_kid_jay_critch/",
    "url": "https://www.youtube.com/watch?v=Nc7UlOMgLEw",
    "author": "lemonchicken91",
    "created_utc": 1702697598,
    "score": 144,
    "daily_sent": false
  },
  {
    "day": "2023-12-16T00:00:00.000Z",
    "id": "18jyvjg",
    "title": "[FRESH VIDEO] Curren$y - All Fucked Up",
    "permalink": "/r/hiphopheads/comments/18jyvjg/fresh_video_curreny_all_fucked_up/",
    "url": "https://www.youtube.com/watch?v=FoMGg8eApI4",
    "author": "ImKrispy",
    "created_utc": 1702755700,
    "score": 55,
    "daily_sent": false
  },
  {
    "day": "2023-12-16T00:00:00.000Z",
    "id": "18jg954",
    "title": "[FRESH] MO JAMS - CONCRETE BOYS (OFFICIAL VIDEO)",
    "permalink": "/r/hiphopheads/comments/18jg954/fresh_mo_jams_concrete_boys_official_video/",
    "url": "https://youtu.be/cnHCsFFCuAU?si=xD34fV3a4JBXZ4hs",
    "author": "spinagainnn",
    "created_utc": 1702691330,
    "score": 44,
    "daily_sent": false
  },
  {
    "day": "2023-12-16T00:00:00.000Z",
    "id": "18k1oq9",
    "title": "[FRESH EP] Varg²™ & RXKNephew - LD50 Vol.1",
    "permalink": "/r/hiphopheads/comments/18k1oq9/fresh_ep_varg²_rxknephew_ld50_vol1/",
    "url": "https://cease2exist.bandcamp.com/album/ld50",
    "author": "darkfar",
    "created_utc": 1702763808,
    "score": 25,
    "daily_sent": false
  },
  {
    "day": "2023-12-16T00:00:00.000Z",
    "id": "18jg7cw",
    "title": "[FRESH ALBUM] Starlito - Love Drug",
    "permalink": "/r/hiphopheads/comments/18jg7cw/fresh_album_starlito_love_drug/",
    "url": "https://open.spotify.com/album/5T5YZB2CYRW2Fey5Nsf527?si=2v4fe-QVScaxnY3js4J3PQ&context=spotify%3Aalbum%3A5T5YZB2CYRW2Fey5Nsf527",
    "author": "Nankuro85",
    "created_utc": 1702691172,
    "score": 23,
    "daily_sent": false
  },
  {
    "day": "2023-12-16T00:00:00.000Z",
    "id": "18jgwh2",
    "title": "[FRESH] Cookin Soul - XMAS (We've Got)",
    "permalink": "/r/hiphopheads/comments/18jgwh2/fresh_cookin_soul_xmas_weve_got/",
    "url": "https://www.youtube.com/watch?v=ikag6KU97lQ",
    "author": "kmad",
    "created_utc": 1702693440,
    "score": 17,
    "daily_sent": false
  },
  {
    "day": "2023-12-16T00:00:00.000Z",
    "id": "18jhgds",
    "title": "[FRESH ALBUM] BIGBABYGUCCI - When You Go to Sleep",
    "permalink": "/r/hiphopheads/comments/18jhgds/fresh_album_bigbabygucci_when_you_go_to_sleep/",
    "url": "https://www.reddit.com/r/hiphopheads/comments/18jhgds/fresh_album_bigbabygucci_when_you_go_to_sleep/",
    "author": "derhyl_",
    "created_utc": 1702695242,
    "score": 9,
    "daily_sent": false
  },
  {
    "day": "2023-12-16T00:00:00.000Z",
    "id": "18jptam",
    "title": "[FRESH] 10KDunkin & Tony Shhnow - D WILL",
    "permalink": "/r/hiphopheads/comments/18jptam/fresh_10kdunkin_tony_shhnow_d_will/",
    "url": "https://youtu.be/nfo_QPX7HfY?si=LXDxI0a2UYemgxIK",
    "author": "Impossible_Joke9645",
    "created_utc": 1702728093,
    "score": 8,
    "daily_sent": false
  },
  {
    "day": "2023-12-16T00:00:00.000Z",
    "id": "18k2sy5",
    "title": "[FRESH ALBUM] Lil Zay Osama - Hood Bible 2",
    "permalink": "/r/hiphopheads/comments/18k2sy5/fresh_album_lil_zay_osama_hood_bible_2/",
    "url": "https://music.apple.com/us/album/hood-bible-2/1720500241",
    "author": "darkfar",
    "created_utc": 1702767028,
    "score": 8,
    "daily_sent": false
  },
  {
    "day": "2023-12-16T00:00:00.000Z",
    "id": "18jiq0p",
    "title": "[FRESH ALBUM] Hunxho - For Her (Deluxe)",
    "permalink": "/r/hiphopheads/comments/18jiq0p/fresh_album_hunxho_for_her_deluxe/",
    "url": "https://music.apple.com/us/album/for-her-deluxe/1720471465",
    "author": "darkfar",
    "created_utc": 1702699485,
    "score": 6,
    "daily_sent": false
  },
  {
    "day": "2023-12-16T00:00:00.000Z",
    "id": "18jh0ba",
    "title": "TonyChoppa - Life's Daily Missions [FRESH]",
    "permalink": "/r/hiphopheads/comments/18jh0ba/tonychoppa_lifes_daily_missions_fresh/",
    "url": "https://youtu.be/gQ3ajcwEjj0?si=R6RdNCDk4JU9yPDe",
    "author": "tingus_ringus",
    "created_utc": 1702693784,
    "score": 5,
    "daily_sent": false
  },
  {
    "day": "2023-12-16T00:00:00.000Z",
    "id": "18jhmh5",
    "title": "[FRESH] Famous Dex, Rich The Kid & Jay Critch - Big Dawg (Directed by Cole Bennett)",
    "permalink": "/r/hiphopheads/comments/18jhmh5/fresh_famous_dex_rich_the_kid_jay_critch_big_dawg/",
    "url": "https://www.youtube.com/watch?v=Nc7UlOMgLEw",
    "author": "Ok-Reveal-9711",
    "created_utc": 1702695804,
    "score": 4,
    "daily_sent": false
  },
  {
    "day": "2023-12-16T00:00:00.000Z",
    "id": "18jze91",
    "title": "[FRESH] Civic - Ethereal Apex 2014: Remastered",
    "permalink": "/r/hiphopheads/comments/18jze91/fresh_civic_ethereal_apex_2014_remastered/",
    "url": "https://on.soundcloud.com/qQaWP8ydBaUotraW8",
    "author": "NostalgiaEthereal2",
    "created_utc": 1702757173,
    "score": 3,
    "daily_sent": false
  },
  {
    "day": "2023-12-16T00:00:00.000Z",
    "id": "18ji5fm",
    "title": "[FRESH] The Skrilla \"On The Radar\" Freestyle (BEAT 2 VERSE)",
    "permalink": "/r/hiphopheads/comments/18ji5fm/fresh_the_skrilla_on_the_radar_freestyle_beat_2/",
    "url": "https://youtu.be/_OrEIIBxgEI?si=7KFJbafcK8HhAT_t",
    "author": "Impossible_Joke9645",
    "created_utc": 1702697557,
    "score": 1,
    "daily_sent": false
  },
  {
    "day": "2023-12-16T00:00:00.000Z",
    "id": "18k03jz",
    "title": "[FRESH] \"Krack Kalisto\" - Estee Nack x SupremeCee",
    "permalink": "/r/hiphopheads/comments/18k03jz/fresh_krack_kalisto_estee_nack_x_supremecee/",
    "url": "https://youtu.be/jfDuNq8QQKs?si=wbci3Ap04pO6YF38",
    "author": "CT-Imagine",
    "created_utc": 1702759180,
    "score": 1,
    "daily_sent": false
  },
  {
    "day": "2023-12-16T00:00:00.000Z",
    "id": "18ji2gf",
    "title": "[FRESH] Rx Papi - Bone Crusher 2 Feat. RXK Nephew (Prod. PERFECT!)",
    "permalink": "/r/hiphopheads/comments/18ji2gf/fresh_rx_papi_bone_crusher_2_feat_rxk_nephew_prod/",
    "url": "https://youtu.be/ZbSygqymF78?si=wwUAxnlxmA3uWNiz",
    "author": "Impossible_Joke9645",
    "created_utc": 1702697290,
    "score": 0,
    "daily_sent": false
  }
]